cloud2cloud/__init__.py
cloud2cloud/interpolator.py
cloud2cloud-0.2.0.dist-info/LICENSE
cloud2cloud-0.2.0.dist-info/METADATA
cloud2cloud-0.2.0.dist-info/WHEEL
cloud2cloud-0.2.0.dist-info/top_level.txt
cloud2cloud-0.2.0.dist-info/RECORD
