Metadata-Version: 2.1
Name: cloud2cloud
Version: 0.2.0
Summary: Cloud interpolator
Home-page: https://gitlab.com/cerfacs/cloud2cloud
Author: Eloi Demolis
Author-email: coop@cerfacs.fr
License: UNKNOWN
Project-URL: Bug Tracker, https://gitlab.com/cerfacs/cloud2cloud/-/issues
Platform: UNKNOWN
Classifier: Programming Language :: Python :: 3.6
Classifier: Programming Language :: Python :: 3.7
Classifier: Programming Language :: Python :: 3.8
Classifier: Programming Language :: Python :: 3.9
Requires-Python: >=3.6
